FPGAflow_esdg-0.3.5.dist-info/METADATA
FPGAflow_esdg-0.3.5.dist-info/RECORD
FPGAflow_esdg-0.3.5.dist-info/WHEEL
FPGAflow_esdg-0.3.5.dist-info/top_level.txt
fpgaflow/__init__.py
fpgaflow/docflow.py
fpgaflow/environmentsetup.py
fpgaflow/fpgavendor_iface.py
fpgaflow/projectflow.py
fpgaflow/projectmanager.py
fpgaflow/vunit_iface.py
fpgaflow/xml2vhdl_iface.py
fpgaflow/helpers/__init__.py
fpgaflow/helpers/arguments.py
fpgaflow/helpers/customlogging.py
fpgaflow/helpers/funcs.py
fpgaflow/helpers/version.py
