Metadata-Version: 2.1
Name: FPGAflow-esdg
Version: 0.3.5
Summary: FPGAFlow scripted tool-flow for FPGA firmware development
Home-page: https://bitbucket.org/mjroberts/fpgaflow
Author: Electronic System Design Group
Author-email: fpgaflow@stfc.ac.uk
License: UNKNOWN
Platform: UNKNOWN
Classifier: Programming Language :: Python :: 2.7
Classifier: License :: OSI Approved :: BSD License
Classifier: Operating System :: POSIX :: Linux
